nlScript/__init__.py
nlScript/autocompleter.py
nlScript/evaluator.py
nlScript/parsednode.py
nlScript/parseexception.py
nlScript/parser.py
nlScript/core/__init__.py
nlScript/core/autocompletion.py
nlScript/core/bnf.py
nlScript/core/defaultparsednode.py
nlScript/core/graphviz.py
nlScript/core/lexer.py
nlScript/core/matcher.py
nlScript/core/named.py
nlScript/core/nonterminal.py
nlScript/core/parsednodefactory.py
nlScript/core/parsingstate.py
nlScript/core/production.py
nlScript/core/rdparser.py
nlScript/core/representssymbol.py
nlScript/core/symbol.py
nlScript/core/terminal.py
nlScript/ebnf/__init__.py
nlScript/ebnf/ebnf.py
nlScript/ebnf/ebnfcore.py
nlScript/ebnf/ebnfparsednodefactory.py
nlScript/ebnf/ebnfparser.py
nlScript/ebnf/ebnfproduction.py
nlScript/ebnf/join.py
nlScript/ebnf/namedrule.py
nlScript/ebnf/optional.py
nlScript/ebnf/orrule.py
nlScript/ebnf/parselistener.py
nlScript/ebnf/plus.py
nlScript/ebnf/repeat.py
nlScript/ebnf/rule.py
nlScript/ebnf/sequence.py
nlScript/ebnf/star.py
nlScript/test/__init__.py
nlScript/test/testautocompletion.py
nlScript/test/testcharacterset.py
nlScript/test/testcolor.py
nlScript/test/testdate.py
nlScript/test/testdatetime.py
nlScript/test/testdigit.py
nlScript/test/testhighlevelparser.py
nlScript/test/testinteger.py
nlScript/test/testjoin.py
nlScript/test/testletter.py
nlScript/test/testmonth.py
nlScript/test/testoptional.py
nlScript/test/testor.py
nlScript/test/testpath.py
nlScript/test/testplus.py
nlScript/test/testrdparser.py
nlScript/test/testrepeat.py
nlScript/test/teststar.py
nlScript/test/testtime.py
nlScript/ui/__init__.py
nlScript/ui/codeeditor.py
nlScript/ui/ui.py
nlScript/util/__init__.py
nlScript/util/completepath.py
nlScript/util/randomstring.py
nlScript/util/range.py
nlScript-0.3.0.dist-info/LICENSE.txt
nlScript-0.3.0.dist-info/METADATA
nlScript-0.3.0.dist-info/WHEEL
nlScript-0.3.0.dist-info/top_level.txt
nlScript-0.3.0.dist-info/RECORD
