Metadata-Version: 2.1
Name: nlScript
Version: 0.3.0
Summary: A framework for creating scripting interfaces based on natural syntax.
Author-email: Benjamin Schmid <bene.schmid@gmail.com>
Project-URL: Homepage, https://github.com/nlScript/nlScript-python
Project-URL: Issues, https://github.com/nlScript/nlScript-python/issues
Classifier: Development Status :: 4 - Beta
Classifier: Intended Audience :: Developers
Classifier: Programming Language :: Python :: 3
Classifier: License :: OSI Approved :: MIT License
Classifier: Operating System :: OS Independent
Classifier: Topic :: Software Development
Classifier: Topic :: Software Development :: User Interfaces
Requires-Python: >=3.10
License-File: LICENSE.txt
Requires-Dist: PySide2
